HISTORY.rst
LICENSE
MANIFEST.in
README.rst
setup.py
tests.py
fn/__init__.py
fn/func.py
fn/iters.py
fn/monad.py
fn/op.py
fn/recur.py
fn/stream.py
fn/underscore.py
fn/uniform.py
fn.egg-info/PKG-INFO
fn.egg-info/SOURCES.txt
fn.egg-info/dependency_links.txt
fn.egg-info/not-zip-safe
fn.egg-info/top_level.txt