Metadata-Version: 1.0
Name: fn
Version: 0.2.13
Summary: Implementation of missing features to enjoy functional programming in Python
Home-page: https://github.com/kachayev/fn.py
Author: Alexey Kachayev
Author-email: kachayev@gmail.com
License: Copyright 2013 Alexey Kachayev
